{
  "name": "pdxcat-nrpe",
  "version": "2.1.1",
  "author": "Computer Action Team",
  "summary": "Puppet module for NRPE",
  "license": "Apache-2.0",
  "source": "https://github.com/pdxcat/puppet-module-nrpe",
  "project_page": "https://github.com/pdxcat/puppet-module-nrpe",
  "issues_url": "https://github.com/pdxcat/puppet-module-nrpe/issues",
  "dependencies": [
  
  ],
  "data_provider": null,
  "operatingsystem_support": [
    {
      "operatingsystem": "RedHat",
      "operatingsystemrelease": [
        "5",
        "6",
        "7"
      ]
    },
    {
      "operatingsystem": "CentOS",
      "operatingsystemrelease": [
        "5",
        "6",
        "7"
      ]
    },
    {
      "operatingsystem": "OracleLinux",
      "operatingsystemrelease": [
        "5",
        "6",
        "7"
      ]
    },
    {
      "operatingsystem": "Scientific",
      "operatingsystemrelease": [
        "5",
        "6",
        "7"
      ]
    },
    {
      "operatingsystem": "Debian",
      "operatingsystemrelease": [
        "6",
        "7"
      ]
    },
    {
      "operatingsystem": "Ubuntu",
      "operatingsystemrelease": [
        "12.04",
        "14.04"
      ]
    },
    {
      "operatingsystem": "Gentoo"
    },
    {
      "operatingsystem": "FreeBSD"
    },
    {
      "operatingsystem": "Solaris"
    },
    {
      "operatingsystem": "Archlinux"
    }
  ],
  "requirements": [
    {
      "name": "pe",
      "version_requirement": ">= 3.2.0"
    },
    {
      "name": "puppet",
      "version_requirement": ">= 3.2.0"
    },
    {
      "name":"example42/yum",
      "version_requirement":"2.x"
    }
  ]
}
